harmonysite/__init__.py
harmonysite/harmony_site.py
harmonysite-0.0.4.dist-info/LICENCE
harmonysite-0.0.4.dist-info/METADATA
harmonysite-0.0.4.dist-info/WHEEL
harmonysite-0.0.4.dist-info/top_level.txt
harmonysite-0.0.4.dist-info/RECORD
