Metadata-Version: 2.1
Name: harmonysite
Version: 0.0.4
Summary: access to the HarmonySite api from python
Author-email: JonJump <daviesjpuk@gmail.com>
License: Copyright (c) 2018 The Python Packaging Authority
Project-URL: Homepage, https://github.com/jonjump/harmonysite
Project-URL: Bug Tracker, https://github.com/jonjump/harmonysite/issues
Classifier: Programming Language :: Python :: 3
Classifier: License :: OSI Approved :: MIT License
Classifier: Operating System :: OS Independent
Requires-Python: >=3.7
License-File: LICENCE
